cameleon_dp/__init__.py
cameleon_dp/bench.py
cameleon_dp/cert_convex.py
cameleon_dp/cert_monge.py
cameleon_dp/cert_monotone.py
cameleon_dp/cli.py
cameleon_dp/ledger.py
cameleon_dp/licensing.py
cameleon_dp/numba_utils.py
cameleon_dp/numeric.py
cameleon_dp/scheduler.py
cameleon_dp/types.py
cameleon_dp/window_detector.py
cameleon_dp/specialists/dc_opt.py
cameleon_dp/specialists/li_chao.py
cameleon_dp/specialists/smawk.py
cameleon_dp-0.2.0.dist-info/licenses/LICENSE
tools/__init__.py
tools/ci_perf.py
tools/license_keygen.py
tools/perf_check.py
tools/perf_metrics_exporter.py
tools/pyspark_loader.py
tools/run_mono_pref.py
tools/sbom_generate.py
tools/smoke_perf.py
tools/snowflake_loader.py
tools/tmp_debug.py
cameleon_dp-0.2.0.dist-info/METADATA
cameleon_dp-0.2.0.dist-info/WHEEL
cameleon_dp-0.2.0.dist-info/entry_points.txt
cameleon_dp-0.2.0.dist-info/top_level.txt
cameleon_dp-0.2.0.dist-info/RECORD
