Metadata-Version: 2.4
Name: cameleon-dp
Version: 0.2.0
Summary: Exact 1-D DP with structure detection (convex, ε‑Monge, ε‑monotone) and auditable ledger
Author: CAMELEON-DP authors
License: MIT
Project-URL: Homepage, https://example.com/cameleon-dp
Classifier: Programming Language :: Python :: 3
Classifier: License :: OSI Approved :: MIT License
Classifier: Operating System :: OS Independent
Requires-Python: >=3.9
License-File: LICENSE
Requires-Dist: numpy>=1.24
Requires-Dist: cloudpickle>=3.0
Requires-Dist: PyNaCl>=1.5
Provides-Extra: plots
Requires-Dist: matplotlib>=3.7; extra == "plots"
Provides-Extra: parquet
Requires-Dist: pyarrow>=12; extra == "parquet"
Provides-Extra: dev
Requires-Dist: pytest>=7.4; extra == "dev"
Requires-Dist: build>=1.2; extra == "dev"
Requires-Dist: twine>=4.0; extra == "dev"
Dynamic: license-file
